firstuseauthenticator/__init__.py
firstuseauthenticator/_version.py
firstuseauthenticator/firstuseauthenticator.py
firstuseauthenticator/templates/__init__.py
firstuseauthenticator/templates/reset.html
jupyterhub_firstuseauthenticator-1.1.0.dist-info/LICENSE
jupyterhub_firstuseauthenticator-1.1.0.dist-info/METADATA
jupyterhub_firstuseauthenticator-1.1.0.dist-info/WHEEL
jupyterhub_firstuseauthenticator-1.1.0.dist-info/entry_points.txt
jupyterhub_firstuseauthenticator-1.1.0.dist-info/top_level.txt
jupyterhub_firstuseauthenticator-1.1.0.dist-info/RECORD
