Metadata-Version: 2.1
Name: jupyterhub-firstuseauthenticator
Version: 1.1.0
Summary: JupyterHub Authenticator that lets users set passwords on first use
Home-page: https://github.com/jupyterhub/firstuseauthenticator
Author: Yuvi Panda, Project Jupyter Contributors
Author-email: yuvipanda@gmail.com
License: BSD-3-Clause
Requires-Python: >=3.6
License-File: LICENSE
Requires-Dist: bcrypt
Requires-Dist: jupyterhub >=1.3
